LICENSE
MANIFEST.in
README.md
requirements.txt
setup.py
spans_and_trees/__init__.py
spans_and_trees.egg-info/PKG-INFO
spans_and_trees.egg-info/SOURCES.txt
spans_and_trees.egg-info/dependency_links.txt
spans_and_trees.egg-info/requires.txt
spans_and_trees.egg-info/top_level.txt