Metadata-Version: 2.1
Name: spans-and-trees
Version: 0.1.4
Summary: Convert between XML trees and span representation
Home-page: https://github.com/jakelever/spans_and_trees
Author: Jake Lever
Author-email: jake.lever@gmail.com
License: MIT
Keywords: xml
Classifier: Development Status :: 4 - Beta
Classifier: Intended Audience :: Developers
Classifier: License :: OSI Approved :: MIT License
Classifier: Programming Language :: Python :: 3.8
License-File: LICENSE
